ms_mint/Chromatogram.py
ms_mint/Mint.py
ms_mint/MintPlotter.py
ms_mint/TargetOptimizer.py
ms_mint/__init__.py
ms_mint/_version.py
ms_mint/filelock.py
ms_mint/filters.py
ms_mint/io.py
ms_mint/matplotlib_tools.py
ms_mint/notebook.py
ms_mint/pca.py
ms_mint/plotly_tools.py
ms_mint/processing.py
ms_mint/standards.py
ms_mint/targets.py
ms_mint/tools.py
ms_mint/version.py
ms_mint/scripts/__init__.py
ms_mint/scripts/ms_mint_convert.py
ms_mint-1.1.1.dist-info/licenses/LICENSE
ms_mint-1.1.1.dist-info/METADATA
ms_mint-1.1.1.dist-info/WHEEL
ms_mint-1.1.1.dist-info/entry_points.txt
ms_mint-1.1.1.dist-info/top_level.txt
ms_mint-1.1.1.dist-info/RECORD
