Metadata-Version: 2.4
Name: ms-mint
Version: 1.1.1
Summary: Python library for large-scale targeted metabolomics.
Author-email: Soren Wacker <swacker@ucalgary.ca>
Project-URL: Homepage, https://github.com/LewisResearchGroup/ms-mint
Classifier: Programming Language :: Python :: 3
Classifier: License :: OSI Approved :: MIT License
Classifier: Operating System :: OS Independent
Requires-Python: >=3.9
License-File: LICENSE
Requires-Dist: six
Requires-Dist: jsonschema
Requires-Dist: entrypoints
Requires-Dist: pygments
Requires-Dist: pexpect
Requires-Dist: decorator
Requires-Dist: pillow
Requires-Dist: lxml
Requires-Dist: pandas
Requires-Dist: matplotlib
Requires-Dist: seaborn
Requires-Dist: pyteomics
Requires-Dist: scikit-learn
Requires-Dist: molmass
Requires-Dist: pymzml
Requires-Dist: plotly
Requires-Dist: colorlover
Requires-Dist: tqdm
Requires-Dist: ipywidgets
Requires-Dist: ipyfilechooser
Requires-Dist: openpyxl
Requires-Dist: pyarrow
Requires-Dist: tables
Requires-Dist: h5py
Requires-Dist: hdf5plugin
Dynamic: license-file
